odoo/addons/picking_carrier_tracking_ref_search/README.rst
odoo/addons/picking_carrier_tracking_ref_search/__init__.py
odoo/addons/picking_carrier_tracking_ref_search/__manifest__.py
odoo/addons/picking_carrier_tracking_ref_search/models/__init__.py
odoo/addons/picking_carrier_tracking_ref_search/models/stock_picking.py
odoo/addons/picking_carrier_tracking_ref_search/readme/CONTRIBUTORS.md
odoo/addons/picking_carrier_tracking_ref_search/readme/DESCRIPTION.md
odoo/addons/picking_carrier_tracking_ref_search/readme/USAGE.md
odoo/addons/picking_carrier_tracking_ref_search/static/description/icon.png
odoo/addons/picking_carrier_tracking_ref_search/static/description/index.html
odoo/addons/picking_carrier_tracking_ref_search/views/stock_picking_views.xml
odoo_addon_picking_carrier_tracking_ref_search-16.0.1.0.0.1.dist-info/METADATA
odoo_addon_picking_carrier_tracking_ref_search-16.0.1.0.0.1.dist-info/WHEEL
odoo_addon_picking_carrier_tracking_ref_search-16.0.1.0.0.1.dist-info/top_level.txt
odoo_addon_picking_carrier_tracking_ref_search-16.0.1.0.0.1.dist-info/RECORD
