Metadata-Version: 2.1
Name: odoo-addon-picking_carrier_tracking_ref_search
Version: 16.0.1.0.0.1
Summary: Search by carrier_tracking_ref in stock pickings
Home-page: https://github.com/sygel-technology/sy-stock-logistics-workflow
Author: Sygel, Odoo Community Association (OCA)
Author-email: support@odoo-community.org
License: AGPL-3
Classifier: Programming Language :: Python
Classifier: Framework :: Odoo
Classifier: Framework :: Odoo :: 16.0
Classifier: License :: OSI Approved :: GNU Affero General Public License v3
Requires-Python: >=3.10
Requires-Dist: odoo<16.1dev,>=16.0a
